propor/__init__.py
propor/get.py
propor/put.py
propor-2019.5.13.dist-info/LICENSE
propor-2019.5.13.dist-info/METADATA
propor-2019.5.13.dist-info/WHEEL
propor-2019.5.13.dist-info/entry_points.txt
propor-2019.5.13.dist-info/top_level.txt
propor-2019.5.13.dist-info/RECORD
