Metadata-Version: 2.1
Name: propor
Version: 2019.5.13
Summary: Project porter.
Home-page: https://github.com/Czw96/propor
Author: Czw_96
Author-email: 459749926@qq.com
License: UNKNOWN
Platform: UNKNOWN
Classifier: Programming Language :: Python :: 3
Classifier: License :: OSI Approved :: MIT License
Classifier: Operating System :: OS Independent
Requires-Dist: paramiko
